README.md
setup.py
hdfs_kernel/__init__.py
hdfs_kernel/command.py
hdfs_kernel/constants.py
hdfs_kernel/exceptions.py
hdfs_kernel/connections/__init__.py
hdfs_kernel/connections/hdfs_client.py
hdfs_kernel/connections/manager.py
hdfs_kernel/kernels/__init__.py
hdfs_kernel/kernels/hdfs/__init__.py
hdfs_kernel/kernels/hdfs/hdfskernel.py
hdfs_kernel/kernels/wrapperkernel/__init__.py
hdfs_kernel/kernels/wrapperkernel/hdfsbase.py
hdfs_kernel/parsers/__init__.py
hdfs_kernel/parsers/code_parser.py
hdfs_kernel/parsers/opt_parser.py
hdfs_kernel/parsers/paths.py
hdfs_kernel/utils/__init__.py
hdfs_kernel/utils/configuration.py
hdfs_kernel/utils/loggers.py
hdfs_kernel/utils/tools.py
jupyter_hdfs_kernel.egg-info/PKG-INFO
jupyter_hdfs_kernel.egg-info/SOURCES.txt
jupyter_hdfs_kernel.egg-info/dependency_links.txt
jupyter_hdfs_kernel.egg-info/requires.txt
jupyter_hdfs_kernel.egg-info/top_level.txt