Metadata-Version: 1.0
Name: jupyter-hdfs-kernel
Version: 1.0.2
Summary: jupyter_hdfs_kernel
Home-page: https://github.com/Jasper912/jupyter_hdfs_kernel.git
Author: huangnj
Author-email: jasper0912@icloud.com
License: MIT License
Keywords: Hdfs Pyhdfs Kernel Ipykernel
Platform: UNKNOWN
